scdev_pd_column_tj/__init__.py
scdev_pd_column_tj/example_charles.py
example_pkg_dev_charles-0.0.1.dist-info/Licenses.txt
example_pkg_dev_charles-0.0.1.dist-info/METADATA
example_pkg_dev_charles-0.0.1.dist-info/WHEEL
example_pkg_dev_charles-0.0.1.dist-info/top_level.txt
example_pkg_dev_charles-0.0.1.dist-info/RECORD
